[
    {
        "geometry": {
            "y": 40.675673000000039, 
            "x": -73.9048339
        }, 
        "attributes": {
            "TOTAL_POPULATION": 0, 
            "CITY": "BROOKLYN", 
            "POST_IMPACT_CAPACITY": 100, 
            "MATCH_TYPE": null, 
            "ZIP": "11233", 
            "OBJECTID": 4, 
            "EVACUATION_CAPACITY": 0, 
            "ORG_ID": null, 
            "SHELTER_NAME": "Kings Hotel", 
            "HOURS_CLOSE": null, 
            "HOURS_OPEN": null, 
            "STATE": "NY", 
            "SHELTER_ID": 349437, 
            "ORG_NAME": null, 
            "SHELTER_STATUS": "OPEN", 
            "ADDRESS": "2416 Atlantic Avenue"
        }
    }, 
    {
        "geometry": {
            "y": 40.621354520000033, 
            "x": -74.074857150000014
        }, 
        "attributes": {
            "TOTAL_POPULATION": 31, 
            "CITY": "STATEN ISLAND", 
            "POST_IMPACT_CAPACITY": 0, 
            "MATCH_TYPE": "A", 
            "ZIP": "10304", 
            "OBJECTID": 8, 
            "EVACUATION_CAPACITY": 150, 
            "ORG_ID": 121425, 
            "SHELTER_NAME": "Bailey Seton", 
            "HOURS_CLOSE": null, 
            "HOURS_OPEN": null, 
            "STATE": "NY", 
            "SHELTER_ID": 349021, 
            "ORG_NAME": "GREATER  NEW YORK  CHAPTER", 
            "SHELTER_STATUS": "OPEN", 
            "ADDRESS": "79 Vanderbilt Ave"
        }
    }, 
    {
        "attributes": {
            "CITY": "BRONX", 
            "ADDRESS": "1315 FRANKLIN AVENUE", 
            "SHELTER_NAME": "ARTURO SCHOMBERG SENIOR CENTER", 
            "HOURS_OPEN": null, 
            "STATE": "NY", 
            "HOURS_CLOSE": null
        }
    }, 
    {
        "attributes": {
            "CITY": "BRONX", 
            "ADDRESS": "990 PELHAM PARKWAY SOUTH", 
            "SHELTER_NAME": "BRONX HOUSE SENIOR CENTER", 
            "HOURS_OPEN": null, 
            "STATE": "NY", 
            "HOURS_CLOSE": null
        }
    }, 
    {
        "attributes": {
            "CITY": "BRONX", 
            "ADDRESS": "515 JACKSON AVENUE", 
            "SHELTER_NAME": "BRONXWORKS E ROBERTS MOORE SENIOR CENTER", 
            "HOURS_OPEN": null, 
            "STATE": "NY", 
            "HOURS_CLOSE": null
        }
    }, 
    {
        "attributes": {
            "CITY": "BRONX", 
            "ADDRESS": "236 EAST TREMONT AVENUE", 
            "SHELTER_NAME": "BRONXWORKS EAST CONCOURSE SENIOR CENTER", 
            "HOURS_OPEN": null, 
            "STATE": "NY", 
            "HOURS_CLOSE": null
        }
    }, 
    {
        "attributes": {
            "CITY": "BRONX", 
            "ADDRESS": "200 WEST TREMONT AVENUE", 
            "SHELTER_NAME": "BRONXWORKS HEIGHTS SENIOR CENTER", 
            "HOURS_OPEN": null, 
            "STATE": "NY", 
            "HOURS_CLOSE": null
        }
    }, 
    {
        "attributes": {
            "CITY": "BRONX", 
            "ADDRESS": "80 EAST 181ST STREET", 
            "SHELTER_NAME": "BRONXWORKS MORRIS INNOVATIVE SR CENTER", 
            "HOURS_OPEN": null, 
            "STATE": "NY", 
            "HOURS_CLOSE": null
        }
    }, 
    {
        "attributes": {
            "CITY": "BRONX", 
            "ADDRESS": "900 GRAND CONCOURSE", 
            "SHELTER_NAME": "CONCOURSE WELLNESS CENTER", 
            "HOURS_OPEN": null, 
            "STATE": "NY", 
            "HOURS_CLOSE": null
        }
    }, 
    {
        "attributes": {
            "CITY": "BRONX", 
            "ADDRESS": "2049 BARTOW AVENUE", 
            "SHELTER_NAME": "CO-OP CITY SENIOR CENTER", 
            "HOURS_OPEN": null, 
            "STATE": "NY", 
            "HOURS_CLOSE": null
        }
    }, 
    {
        "attributes": {
            "CITY": "BRONX", 
            "ADDRESS": "177 DREISER LOOP", 
            "SHELTER_NAME": "DREISER SENIOR CENTER", 
            "HOURS_OPEN": null, 
            "STATE": "NY", 
            "HOURS_CLOSE": null
        }
    }, 
    {
        "attributes": {
            "CITY": "BRONX", 
            "ADDRESS": "1068 GERARD AVENUE", 
            "SHELTER_NAME": "HOPE OF ISRAEL SENIOR CENTER", 
            "HOURS_OPEN": null, 
            "STATE": "NY", 
            "HOURS_CLOSE": null
        }
    }, 
    {
        "attributes": {
            "CITY": "BRONX", 
            "ADDRESS": "787 E. 149TH ST. (temporary)", 
            "SHELTER_NAME": "IPR/HE BETANCES SENIOR CENTER", 
            "HOURS_OPEN": null, 
            "STATE": "NY", 
            "HOURS_CLOSE": null
        }
    }, 
    {
        "attributes": {
            "CITY": "BRONX", 
            "ADDRESS": "1776 STORY AVENUE", 
            "SHELTER_NAME": "JAMES MONROE SENIOR CENTER", 
            "HOURS_OPEN": null, 
            "STATE": "NY", 
            "HOURS_CLOSE": null
        }
    }, 
    {
        "attributes": {
            "CITY": "BRONX", 
            "ADDRESS": "1220 EAST 229TH STREET", 
            "SHELTER_NAME": "JASA BAY-EDEN SENIOR CENTER", 
            "HOURS_OPEN": null, 
            "STATE": "NY", 
            "HOURS_CLOSE": null
        }
    }, 
    {
        "attributes": {
            "CITY": "BRONX", 
            "ADDRESS": "2705 SCHLEY AVENUE", 
            "SHELTER_NAME": "JASA THROGS NECK SENIOR CENTER", 
            "HOURS_OPEN": null, 
            "STATE": "NY", 
            "HOURS_CLOSE": null
        }
    }, 
    {
        "attributes": {
            "CITY": "BRONX", 
            "ADDRESS": "625 CASTLE HILL AVENUE", 
            "SHELTER_NAME": "KIPS BAY CASTLE HILL SENIOR CENTER", 
            "HOURS_OPEN": null, 
            "STATE": "NY", 
            "HOURS_CLOSE": null
        }
    }, 
    {
        "attributes": {
            "CITY": "BRONX", 
            "ADDRESS": "5365 BROADWAY", 
            "SHELTER_NAME": "MARBLE HILL SENIOR CENTER", 
            "HOURS_OPEN": null, 
            "STATE": "NY", 
            "HOURS_CLOSE": null
        }
    }, 
    {
        "attributes": {
            "CITY": "BRONX", 
            "ADDRESS": "372 EAST 152ND STREET", 
            "SHELTER_NAME": "MELROSE MOTT HAVEN SENIOR CENTER", 
            "HOURS_OPEN": null, 
            "STATE": "NY", 
            "HOURS_CLOSE": null
        }
    }, 
    {
        "attributes": {
            "CITY": "BRONX", 
            "ADDRESS": "188 LINCOLN AVENUE", 
            "SHELTER_NAME": "MITCHELL HOUSES", 
            "HOURS_OPEN": null, 
            "STATE": "NY", 
            "HOURS_CLOSE": null
        }
    }, 
    {
        "attributes": {
            "CITY": "BRONX", 
            "ADDRESS": "3450 DEKALB AVENUE", 
            "SHELTER_NAME": "MOSHOLU MONTEFIORE SENIOR CENTER", 
            "HOURS_OPEN": null, 
            "STATE": "NY", 
            "HOURS_CLOSE": null
        }
    }, 
    {
        "attributes": {
            "CITY": "BRONX", 
            "ADDRESS": "2405 SOUTHERN BOULEVARD", 
            "SHELTER_NAME": "MT CARMEL CENTER FOR SR CITIZENS", 
            "HOURS_OPEN": null, 
            "STATE": "NY", 
            "HOURS_CLOSE": null
        }
    }, 
    {
        "attributes": {
            "CITY": "BRONX", 
            "ADDRESS": "910 EAST 172ND STREET", 
            "SHELTER_NAME": "NEIGHBORHOOD SHOPP CASA BORICUA SR CTR", 
            "HOURS_OPEN": null, 
            "STATE": "NY", 
            "HOURS_CLOSE": null
        }
    }, 
    {
        "attributes": {
            "CITY": "BRONX", 
            "ADDRESS": "735 EAST 152ND STREET", 
            "SHELTER_NAME": "NEIGHBORHOOD SHOPP LEON SENIOR CENTER", 
            "HOURS_OPEN": null, 
            "STATE": "NY", 
            "HOURS_CLOSE": null
        }
    }, 
    {
        "attributes": {
            "CITY": "BRONX", 
            "ADDRESS": "2968 BRUCKNER BOULEVARD", 
            "SHELTER_NAME": "NORTHEAST BRONX SENIOR CITIZEN CENTER", 
            "HOURS_OPEN": null, 
            "STATE": "NY", 
            "HOURS_CLOSE": null
        }
    }, 
    {
        "attributes": {
            "CITY": "BRONX", 
            "ADDRESS": "644 ADEE AVENUE", 
            "SHELTER_NAME": "PARKSIDE SENIOR CENTER", 
            "HOURS_OPEN": null, 
            "STATE": "NY", 
            "HOURS_CLOSE": null
        }
    }, 
    {
        "attributes": {
            "CITY": "BRONX", 
            "ADDRESS": "325 EAST 156TH STREET", 
            "SHELTER_NAME": "PSS ANDREW JACKSON SENIOR CENTER", 
            "HOURS_OPEN": null, 
            "STATE": "NY", 
            "HOURS_CLOSE": null
        }
    }, 
    {
        "attributes": {
            "CITY": "BRONX", 
            "ADDRESS": "1181 NELSON AVENUE", 
            "SHELTER_NAME": "PSS HIGHBRIDGE SENIOR CENTER", 
            "HOURS_OPEN": null, 
            "STATE": "NY", 
            "HOURS_CLOSE": null
        }
    }, 
    {
        "attributes": {
            "CITY": "BRONX", 
            "ADDRESS": "950 UNION AVENUE", 
            "SHELTER_NAME": "PSS-DAVIDSON SENIOR CENTER", 
            "HOURS_OPEN": null, 
            "STATE": "NY", 
            "HOURS_CLOSE": null
        }
    }, 
    {
        "attributes": {
            "CITY": "BRONX", 
            "ADDRESS": "3450 BOSTON RD", 
            "SHELTER_NAME": "RAIN BOSTON EAST SENIOR CENTER", 
            "HOURS_OPEN": null, 
            "STATE": "NY", 
            "HOURS_CLOSE": null
        }
    }, 
    {
        "attributes": {
            "CITY": "BRONX", 
            "ADDRESS": "2424 BOSTON RD", 
            "SHELTER_NAME": "RAIN BOSTON ROAD SENIOR CENTER", 
            "HOURS_OPEN": null, 
            "STATE": "NY", 
            "HOURS_CLOSE": null
        }
    }, 
    {
        "attributes": {
            "CITY": "BRONX", 
            "ADDRESS": "3540 BIVONA ST", 
            "SHELTER_NAME": "RAIN BOSTON SECOR SENIOR CENTER", 
            "HOURS_OPEN": null, 
            "STATE": "NY", 
            "HOURS_CLOSE": null
        }
    }, 
    {
        "attributes": {
            "CITY": "BRONX", 
            "ADDRESS": "1246 BURKE AVE", 
            "SHELTER_NAME": "RAIN EASTCHESTER SENIOR CENTER", 
            "HOURS_OPEN": null, 
            "STATE": "NY", 
            "HOURS_CLOSE": null
        }
    }, 
    {
        "attributes": {
            "CITY": "BRONX", 
            "ADDRESS": "3377 WHITE PLAINS RD", 
            "SHELTER_NAME": "RAIN GUNHILL SENIOR CENTER", 
            "HOURS_OPEN": null, 
            "STATE": "NY", 
            "HOURS_CLOSE": null
        }
    }, 
    {
        "attributes": {
            "CITY": "BRONX", 
            "ADDRESS": "3035 MIDDLETOWN RD", 
            "SHELTER_NAME": "RAIN MIDDLETOWN SENIOR CENTER", 
            "HOURS_OPEN": null, 
            "STATE": "NY", 
            "HOURS_CLOSE": null
        }
    }, 
    {
        "attributes": {
            "CITY": "BRONX", 
            "ADDRESS": "720 NEREID AVE", 
            "SHELTER_NAME": "RAIN NEREID SENIOR CENTER", 
            "HOURS_OPEN": null, 
            "STATE": "NY", 
            "HOURS_CLOSE": null
        }
    }, 
    {
        "attributes": {
            "CITY": "BRONX", 
            "ADDRESS": "1380 METROPOLITAN AVE", 
            "SHELTER_NAME": "RAIN PARKCHESTER SENIOR CENTER", 
            "HOURS_OPEN": null, 
            "STATE": "NY", 
            "HOURS_CLOSE": null
        }
    }, 
    {
        "attributes": {
            "CITY": "BRONX", 
            "ADDRESS": "2600 NETHERLAND AVENUE", 
            "SHELTER_NAME": "RIVERDALE SENIOR CENTER", 
            "HOURS_OPEN": null, 
            "STATE": "NY", 
            "HOURS_CLOSE": null
        }
    }, 
    {
        "attributes": {
            "CITY": "BRONX", 
            "ADDRESS": "5625 ARLINGTON AVENUE", 
            "SHELTER_NAME": "RIVERDALE Y SENIOR CENTER", 
            "HOURS_OPEN": null, 
            "STATE": "NY", 
            "HOURS_CLOSE": null
        }
    }, 
    {
        "attributes": {
            "CITY": "BRONX", 
            "ADDRESS": "887 SOUTHERN BOULEVARD", 
            "SHELTER_NAME": "SEBCO SENIOR PROGRAMS", 
            "HOURS_OPEN": null, 
            "STATE": "NY", 
            "HOURS_CLOSE": null
        }
    }, 
    {
        "attributes": {
            "CITY": "BRONX", 
            "ADDRESS": "243 EAST 204TH STREET", 
            "SHELTER_NAME": "SISTER ANNUNCIATA BETHEL SENIOR CENTER", 
            "HOURS_OPEN": null, 
            "STATE": "NY", 
            "HOURS_CLOSE": null
        }
    }, 
    {
        "attributes": {
            "CITY": "BRONX", 
            "ADDRESS": "2070 CLINTON AVENUE", 
            "SHELTER_NAME": "THOMAS L. GUESS COMMUNITY SENIOR CENTER", 
            "HOURS_OPEN": null, 
            "STATE": "NY", 
            "HOURS_CLOSE": null
        }
    }, 
    {
        "attributes": {
            "CITY": "BRONX", 
            "ADDRESS": "3880 SEDGWICK AVENUE", 
            "SHELTER_NAME": "VAN CORTLANDT SENIOR CENTER", 
            "HOURS_OPEN": null, 
            "STATE": "NY", 
            "HOURS_CLOSE": null
        }
    }, 
    {
        "attributes": {
            "CITY": "BRONX", 
            "ADDRESS": "1320 WEBSTER AVENUE", 
            "SHELTER_NAME": "WILLIAM HODSON SENIOR CENTER", 
            "HOURS_OPEN": null, 
            "STATE": "NY", 
            "HOURS_CLOSE": null
        }
    }, 
    {
        "attributes": {
            "CITY": "BROOKLYN", 
            "ADDRESS": "10315 FARRAGUT ROAD", 
            "SHELTER_NAME": "ABE STARK SENIOR CENTER", 
            "HOURS_OPEN": null, 
            "STATE": "NY", 
            "HOURS_CLOSE": null
        }
    }, 
    {
        "attributes": {
            "CITY": "BROOKLYN", 
            "ADDRESS": "5901 13TH AVENUE", 
            "SHELTER_NAME": "AMICO 59TH STREET SENIOR CENTER", 
            "HOURS_OPEN": null, 
            "STATE": "NY", 
            "HOURS_CLOSE": null
        }
    }, 
    {
        "attributes": {
            "CITY": "BROOKLYN", 
            "ADDRESS": "411 OVINGTON AVENUE", 
            "SHELTER_NAME": "BAY RIDGE CENTER FOR OLDER ADULTS", 
            "HOURS_OPEN": null, 
            "STATE": "NY", 
            "HOURS_CLOSE": null
        }
    }, 
    {
        "attributes": {
            "CITY": "BROOKLYN", 
            "ADDRESS": "545 60TH STREET", 
            "SHELTER_NAME": "BCA 6TH AVENUE SENIOR CENTER", 
            "HOURS_OPEN": null, 
            "STATE": "NY", 
            "HOURS_CLOSE": null
        }
    }, 
    {
        "attributes": {
            "CITY": "BROOKLYN", 
            "ADDRESS": "7802 BAY PARKWAY", 
            "SHELTER_NAME": "BENSONHURST SENIOR CENTER", 
            "HOURS_OPEN": null, 
            "STATE": "NY", 
            "HOURS_CLOSE": null
        }
    }, 
    {
        "attributes": {
            "CITY": "BROOKLYN", 
            "ADDRESS": "2335 BERGEN AVENUE", 
            "SHELTER_NAME": "BERGEN BEACH YOUTH ORGANIZATION INC.", 
            "HOURS_OPEN": null, 
            "STATE": "NY", 
            "HOURS_CLOSE": null
        }
    }, 
    {
        "attributes": {
            "CITY": "BROOKLYN", 
            "ADDRESS": "80 SEIGEL STREET", 
            "SHELTER_NAME": "BORINQUEN PLAZA NUTRITION CENTER", 
            "HOURS_OPEN": null, 
            "STATE": "NY", 
            "HOURS_CLOSE": null
        }
    }, 
    {
        "attributes": {
            "CITY": "BROOKLYN", 
            "ADDRESS": "5602 11TH AVENUE", 
            "SHELTER_NAME": "BORO PARK SENIOR CENTER", 
            "HOURS_OPEN": null, 
            "STATE": "NY", 
            "HOURS_CLOSE": null
        }
    }, 
    {
        "attributes": {
            "CITY": "BROOKLYN", 
            "ADDRESS": "4912 14TH AVENUE", 
            "SHELTER_NAME": "BORO PARK YM-YWHA SENIOR CENTER", 
            "HOURS_OPEN": null, 
            "STATE": "NY", 
            "HOURS_CLOSE": null
        }
    }, 
    {
        "attributes": {
            "CITY": "BROOKLYN", 
            "ADDRESS": "817 AVENUE H", 
            "SHELTER_NAME": "BROOKDALE SENIOR CITIZENS CENTER", 
            "HOURS_OPEN": null, 
            "STATE": "NY", 
            "HOURS_CLOSE": null
        }
    }, 
    {
        "attributes": {
            "CITY": "BROOKLYN", 
            "ADDRESS": "5701 AVENUE H", 
            "SHELTER_NAME": "CCNS GLENWOOD SENIOR CENTER", 
            "HOURS_OPEN": null, 
            "STATE": "NY", 
            "HOURS_CLOSE": null
        }
    }, 
    {
        "attributes": {
            "CITY": "BROOKLYN", 
            "ADDRESS": "715 LEONARD STREET", 
            "SHELTER_NAME": "CCNS MCGUINESS NORTHSIDE SENIOR CENTER", 
            "HOURS_OPEN": null, 
            "STATE": "NY", 
            "HOURS_CLOSE": null
        }
    }, 
    {
        "attributes": {
            "CITY": "BROOKLYN", 
            "ADDRESS": "1230 63RD STREET", 
            "SHELTER_NAME": "CCNS NARROWS SENIOR CENTER", 
            "HOURS_OPEN": null, 
            "STATE": "NY", 
            "HOURS_CLOSE": null
        }
    }, 
    {
        "attributes": {
            "CITY": "BROOKLYN", 
            "ADDRESS": "179 NORTH 6TH STREET", 
            "SHELTER_NAME": "CCNS NORTHSIDE SENIOR CENTER", 
            "HOURS_OPEN": null, 
            "STATE": "NY", 
            "HOURS_CLOSE": null
        }
    }, 
    {
        "attributes": {
            "CITY": "BROOKLYN", 
            "ADDRESS": "230 KINGSTON AVENUE", 
            "SHELTER_NAME": "CCNS SAINT LOUIS SENIOR CENTER", 
            "HOURS_OPEN": null, 
            "STATE": "NY", 
            "HOURS_CLOSE": null
        }
    }, 
    {
        "attributes": {
            "CITY": "BROOKLYN", 
            "ADDRESS": "55 PIERREPONT STREET", 
            "SHELTER_NAME": "CCNS ST CHARLES JUBILEE SENIOR CENTER", 
            "HOURS_OPEN": null, 
            "STATE": "NY", 
            "HOURS_CLOSE": null
        }
    }, 
    {
        "attributes": {
            "CITY": "BROOKLYN", 
            "ADDRESS": "3643 NOSTRAND AVENUE", 
            "SHELTER_NAME": "CCNS THE BAY SENIOR CENTER", 
            "HOURS_OPEN": null, 
            "STATE": "NY", 
            "HOURS_CLOSE": null
        }
    }, 
    {
        "attributes": {
            "CITY": "BROOKLYN", 
            "ADDRESS": "720 EAST NEW YORK AVENUE", 
            "SHELTER_NAME": "CHRISTOPHER C BLENMAN SENIOR CENTER", 
            "HOURS_OPEN": null, 
            "STATE": "NY", 
            "HOURS_CLOSE": null
        }
    }, 
    {
        "attributes": {
            "CITY": "BROOKLYN", 
            "ADDRESS": "1001 QUENTIN ROAD", 
            "SHELTER_NAME": "COUNCIL CENTER FOR SENIOR CITIZENS", 
            "HOURS_OPEN": null, 
            "STATE": "NY", 
            "HOURS_CLOSE": null
        }
    }, 
    {
        "attributes": {
            "CITY": "BROOKLYN", 
            "ADDRESS": "3208 FULTON STREET", 
            "SHELTER_NAME": "CYPRESS HILLS FULTON ST SR CENTER", 
            "HOURS_OPEN": null, 
            "STATE": "NY", 
            "HOURS_CLOSE": null
        }
    }, 
    {
        "attributes": {
            "CITY": "BROOKLYN", 
            "ADDRESS": "9 NOLL STREET", 
            "SHELTER_NAME": "DIANA JONES SENIOR CENTER", 
            "HOURS_OPEN": null, 
            "STATE": "NY", 
            "HOURS_CLOSE": null
        }
    }, 
    {
        "attributes": {
            "CITY": "BROOKLYN", 
            "ADDRESS": "1419 DORCHESTER ROAD", 
            "SHELTER_NAME": "DORCHESTER SENIOR CENTER", 
            "HOURS_OPEN": null, 
            "STATE": "NY", 
            "HOURS_CLOSE": null
        }
    }, 
    {
        "attributes": {
            "CITY": "BROOKLYN", 
            "ADDRESS": "196 ALBANY AVENUE", 
            "SHELTER_NAME": "FORT GREENE ALBANY SENIOR CENTER", 
            "HOURS_OPEN": null, 
            "STATE": "NY", 
            "HOURS_CLOSE": null
        }
    }, 
    {
        "attributes": {
            "CITY": "BROOKLYN", 
            "ADDRESS": "2702 LINDEN BOULEVARD", 
            "SHELTER_NAME": "FGC TERESA MOORE SENIOR CENTER", 
            "HOURS_OPEN": null, 
            "STATE": "NY", 
            "HOURS_CLOSE": null
        }
    }, 
    {
        "attributes": {
            "CITY": "BROOKLYN", 
            "ADDRESS": "951-963 OCEAN AVENUE", 
            "SHELTER_NAME": "FORT GREENE HAZEL BROOKS SENIOR CENTER", 
            "HOURS_OPEN": null, 
            "STATE": "NY", 
            "HOURS_CLOSE": null
        }
    }, 
    {
        "attributes": {
            "CITY": "BROOKLYN", 
            "ADDRESS": "19 GRANT SQUARE", 
            "SHELTER_NAME": "FT GREENE GRANT SQUARE SENIOR CENTER", 
            "HOURS_OPEN": null, 
            "STATE": "NY", 
            "HOURS_CLOSE": null
        }
    }, 
    {
        "attributes": {
            "CITY": "BROOKLYN", 
            "ADDRESS": "69 MCDONOUGH STREET", 
            "SHELTER_NAME": "FT GREENE STUYVESANT HEIGHTS SENIOR CTR", 
            "HOURS_OPEN": null, 
            "STATE": "NY", 
            "HOURS_CLOSE": null
        }
    }, 
    {
        "attributes": {
            "CITY": "BROOKLYN", 
            "ADDRESS": "966 FULTON STREET", 
            "SHELTER_NAME": "GRACE AGARD HAREWOOD SENIOR CENTER", 
            "HOURS_OPEN": null, 
            "STATE": "NY", 
            "HOURS_CLOSE": null
        }
    }, 
    {
        "attributes": {
            "CITY": "BROOKLYN", 
            "ADDRESS": "447 KINGSBOROUGH 4th WALK", 
            "SHELTER_NAME": "H GILROY SENIOR CENTER", 
            "HOURS_OPEN": null, 
            "STATE": "NY", 
            "HOURS_CLOSE": null
        }
    }, 
    {
        "attributes": {
            "CITY": "BROOKLYN", 
            "ADDRESS": "7907 NEW UTRECHT AVE", 
            "SHELTER_NAME": "HOMECREST BENSONHURST SENIOR CENTER", 
            "HOURS_OPEN": null, 
            "STATE": "NY", 
            "HOURS_CLOSE": null
        }
    }, 
    {
        "attributes": {
            "CITY": "BROOKLYN", 
            "ADDRESS": "195 LINDEN STREET", 
            "SHELTER_NAME": "HOPE GARDENS SENIOR CENTER", 
            "HOURS_OPEN": null, 
            "STATE": "NY", 
            "HOURS_CLOSE": null
        }
    }, 
    {
        "attributes": {
            "CITY": "BROOKLYN", 
            "ADDRESS": "6222 23RD AVENUE", 
            "SHELTER_NAME": "HOUSE OF JACOB SENIOR CENTER", 
            "HOURS_OPEN": null, 
            "STATE": "NY", 
            "HOURS_CLOSE": null
        }
    }, 
    {
        "attributes": {
            "CITY": "BROOKLYN", 
            "ADDRESS": "114 TAYLOR STREET", 
            "SHELTER_NAME": "INDEPENDENCE TOWERS ACTIVE ADULTS", 
            "HOURS_OPEN": null, 
            "STATE": "NY", 
            "HOURS_CLOSE": null
        }
    }, 
    {
        "attributes": {
            "CITY": "BROOKLYN", 
            "ADDRESS": "9502 SEAVIEW AVENUE", 
            "SHELTER_NAME": "JASA HES SENIOR CENTER", 
            "HOURS_OPEN": null, 
            "STATE": "NY", 
            "HOURS_CLOSE": null
        }
    }, 
    {
        "attributes": {
            "CITY": "BROOKLYN", 
            "ADDRESS": "2880 WEST 12TH STREET", 
            "SHELTER_NAME": "JASA LUNA PARK SENIOR CENTER", 
            "HOURS_OPEN": null, 
            "STATE": "NY", 
            "HOURS_CLOSE": null
        }
    }, 
    {
        "attributes": {
            "CITY": "BROOKLYN", 
            "ADDRESS": "60 WEST END AVENUE", 
            "SHELTER_NAME": "JASA MANHATTAN BEACH SENIOR CENTER", 
            "HOURS_OPEN": null, 
            "STATE": "NY", 
            "HOURS_CLOSE": null
        }
    }, 
    {
        "attributes": {
            "CITY": "BROOKLYN", 
            "ADDRESS": "3601 SURF AVENUE", 
            "SHELTER_NAME": "JASA SCHEUER HOUSE OF CONEY ISL SR CTR", 
            "HOURS_OPEN": null, 
            "STATE": "NY", 
            "HOURS_CLOSE": null
        }
    }, 
    {
        "attributes": {
            "CITY": "BROOKLYN", 
            "ADDRESS": "161 CORBIN PLACE", 
            "SHELTER_NAME": "JASA SENIOR ALLIANCE SENIOR CENTER", 
            "HOURS_OPEN": null, 
            "STATE": "NY", 
            "HOURS_CLOSE": null
        }
    }, 
    {
        "attributes": {
            "CITY": "BROOKLYN", 
            "ADDRESS": "3300 CONEY ISLAND AVENUE", 
            "SHELTER_NAME": "JASA SHOREFRONT SENIOR CENTER", 
            "HOURS_OPEN": null, 
            "STATE": "NY", 
            "HOURS_CLOSE": null
        }
    }, 
    {
        "attributes": {
            "CITY": "BROOKLYN", 
            "ADDRESS": "1540 VAN SICLEN AVENUE", 
            "SHELTER_NAME": "JASA STARRETT CITY SENIOR CENTER", 
            "HOURS_OPEN": null, 
            "STATE": "NY", 
            "HOURS_CLOSE": null
        }
    }, 
    {
        "attributes": {
            "CITY": "BROOKLYN", 
            "ADDRESS": "202 GRAHAM AVENUE", 
            "SHELTER_NAME": "JASA WILLIAMSBURG SENIOR CENTER", 
            "HOURS_OPEN": null, 
            "STATE": "NY", 
            "HOURS_CLOSE": null
        }
    }, 
    {
        "attributes": {
            "CITY": "BROOKLYN", 
            "ADDRESS": "2600 OCEAN AVENUE", 
            "SHELTER_NAME": "JAY SENIOR CENTER", 
            "HOURS_OPEN": null, 
            "STATE": "NY", 
            "HOURS_CLOSE": null
        }
    }, 
    {
        "attributes": {
            "CITY": "BROOKLYN", 
            "ADDRESS": "176 JAVA STREET", 
            "SHELTER_NAME": "KRAKUS LUNCHEON CLUB SENIOR CENTER", 
            "HOURS_OPEN": null, 
            "STATE": "NY", 
            "HOURS_CLOSE": null
        }
    }, 
    {
        "attributes": {
            "CITY": "BROOKLYN", 
            "ADDRESS": "201 SOUTH 4TH STREET", 
            "SHELTER_NAME": "LOS SURES SENIOR CENTER", 
            "HOURS_OPEN": null, 
            "STATE": "NY", 
            "HOURS_CLOSE": null
        }
    }, 
    {
        "attributes": {
            "CITY": "BROOKLYN", 
            "ADDRESS": "400 HART STREET", 
            "SHELTER_NAME": "MARIA LAWTON SENIOR CENTER", 
            "HOURS_OPEN": null, 
            "STATE": "NY", 
            "HOURS_CLOSE": null
        }
    }, 
    {
        "attributes": {
            "CITY": "BROOKLYN", 
            "ADDRESS": "2298 WEST 8TH STREET", 
            "SHELTER_NAME": "MARLBORO SENIOR CENTER", 
            "HOURS_OPEN": null, 
            "STATE": "NY", 
            "HOURS_CLOSE": null
        }
    }, 
    {
        "attributes": {
            "CITY": "BROOKLYN", 
            "ADDRESS": "4815 AVENUE I", 
            "SHELTER_NAME": "MIDWOOD SENIOR CENTER", 
            "HOURS_OPEN": null, 
            "STATE": "NY", 
            "HOURS_CLOSE": null
        }
    }, 
    {
        "attributes": {
            "CITY": "BROOKLYN", 
            "ADDRESS": "1625 OCEAN AVENUE", 
            "SHELTER_NAME": "MIDWOOD SENIOR LEAGUE SATELITE", 
            "HOURS_OPEN": null, 
            "STATE": "NY", 
            "HOURS_CLOSE": null
        }
    }, 
    {
        "attributes": {
            "CITY": "BROOKLYN", 
            "ADDRESS": "77-11 18TH AVENUE", 
            "SHELTER_NAME": "MOOSE LODGE SENIOR CENTER", 
            "HOURS_OPEN": null, 
            "STATE": "NY", 
            "HOURS_CLOSE": null
        }
    }, 
    {
        "attributes": {
            "CITY": "BROOKLYN", 
            "ADDRESS": "1960 EAST 7TH STREET", 
            "SHELTER_NAME": "OCEAN PARKWAY SENIOR CITIZENS CENTER", 
            "HOURS_OPEN": null, 
            "STATE": "NY", 
            "HOURS_CLOSE": null
        }
    }, 
    {
        "attributes": {
            "CITY": "BROOKLYN", 
            "ADDRESS": "463A 7TH STREET", 
            "SHELTER_NAME": "PARK SLOPE SENIOR CITIZENS CENTER", 
            "HOURS_OPEN": null, 
            "STATE": "NY", 
            "HOURS_CLOSE": null
        }
    }, 
    {
        "attributes": {
            "CITY": "BROOKLYN", 
            "ADDRESS": "895 PENNSYLVANIA AVENUE", 
            "SHELTER_NAME": "PENN WORTMAN ACTIVE ADULTS", 
            "HOURS_OPEN": null, 
            "STATE": "NY", 
            "HOURS_CLOSE": null
        }
    }, 
    {
        "attributes": {
            "CITY": "BROOKLYN", 
            "ADDRESS": "283 PROSPECT AVENUE", 
            "SHELTER_NAME": "PROSPECT HILL SENIOR SERVICES CENTER", 
            "HOURS_OPEN": null, 
            "STATE": "NY", 
            "HOURS_CLOSE": null
        }
    }, 
    {
        "attributes": {
            "CITY": "BROOKLYN", 
            "ADDRESS": "110 WEST 9TH STREET (temporary)", 
            "SHELTER_NAME": "RED HOOK SENIOR CENTER", 
            "HOURS_OPEN": null, 
            "STATE": "NY", 
            "HOURS_CLOSE": null
        }
    }, 
    {
        "attributes": {
            "CITY": "BROOKLYN", 
            "ADDRESS": "3304 CLARENDON ROAD", 
            "SHELTER_NAME": "REMSEN-SENIOR ACTION SENIOR CENTER", 
            "HOURS_OPEN": null, 
            "STATE": "NY", 
            "HOURS_CLOSE": null
        }
    }, 
    {
        "attributes": {
            "CITY": "BROOKLYN", 
            "ADDRESS": "319 STANHOPE STREET", 
            "SHELTER_NAME": "RIDGEWOOD BUSHWICK SENIOR CENTER", 
            "HOURS_OPEN": null, 
            "STATE": "NY", 
            "HOURS_CLOSE": null
        }
    }, 
    {
        "attributes": {
            "CITY": "BROOKLYN", 
            "ADDRESS": "460 DUMONT AVENUE", 
            "SHELTER_NAME": "ROSETTA GASTON SENIOR CENTER", 
            "HOURS_OPEN": null, 
            "STATE": "NY", 
            "HOURS_CLOSE": null
        }
    }, 
    {
        "attributes": {
            "CITY": "BROOKLYN", 
            "ADDRESS": "1175 GATES AVENUE", 
            "SHELTER_NAME": "ROUNDTABLE SENIOR CITIZENS CENTER", 
            "HOURS_OPEN": null, 
            "STATE": "NY", 
            "HOURS_CLOSE": null
        }
    }, 
    {
        "attributes": {
            "CITY": "BROOKLYN", 
            "ADDRESS": "331 HAWTHORNE STREET", 
            "SHELTER_NAME": "SAINT GABRIELS SENIOR CENTER", 
            "HOURS_OPEN": null, 
            "STATE": "NY", 
            "HOURS_CLOSE": null
        }
    }, 
    {
        "attributes": {
            "CITY": "BROOKLYN", 
            "ADDRESS": "485 KINGS HIGHWAY", 
            "SHELTER_NAME": "SEPHARDIC MULTI SERVICE SENIOR CENTER", 
            "HOURS_OPEN": null, 
            "STATE": "NY", 
            "HOURS_CLOSE": null
        }
    }, 
    {
        "attributes": {
            "CITY": "BROOKLYN", 
            "ADDRESS": "483 ALBANY AVENUE", 
            "SHELTER_NAME": "SHALOM SENIOR CENTER", 
            "HOURS_OPEN": null, 
            "STATE": "NY", 
            "HOURS_CLOSE": null
        }
    }, 
    {
        "attributes": {
            "CITY": "BROOKLYN", 
            "ADDRESS": "9000 SHORE ROAD", 
            "SHELTER_NAME": "SHORE HILL NEIGHBORHOOD CENTER", 
            "HOURS_OPEN": null, 
            "STATE": "NY", 
            "HOURS_CLOSE": null
        }
    }, 
    {
        "attributes": {
            "CITY": "BROOKLYN", 
            "ADDRESS": "550 OCEAN PARKWAY", 
            "SHELTER_NAME": "SR CITIZENS LEAGUE OF FLATBUSH SR CENTER", 
            "HOURS_OPEN": null, 
            "STATE": "NY", 
            "HOURS_CLOSE": null
        }
    }, 
    {
        "attributes": {
            "CITY": "BROOKLYN", 
            "ADDRESS": "4520 FOURTH AVENUE", 
            "SHELTER_NAME": "SUNSET PARK SENIOR CENTER", 
            "HOURS_OPEN": null, 
            "STATE": "NY", 
            "HOURS_CLOSE": null
        }
    }, 
    {
        "attributes": {
            "CITY": "BROOKLYN", 
            "ADDRESS": "211 AINSLIE STREET", 
            "SHELTER_NAME": "SWINGING 60S SENIOR CENTER", 
            "HOURS_OPEN": null, 
            "STATE": "NY", 
            "HOURS_CLOSE": null
        }
    }, 
    {
        "attributes": {
            "CITY": "BROOKLYN", 
            "ADDRESS": "630 MOTHER GASTON BOULEVARD", 
            "SHELTER_NAME": "TILDEN SENIOR CENTER", 
            "HOURS_OPEN": null, 
            "STATE": "NY", 
            "HOURS_CLOSE": null
        }
    }, 
    {
        "attributes": {
            "CITY": "BROOKLYN", 
            "ADDRESS": "460 ATLANTIC AVENUE", 
            "SHELTER_NAME": "TIMES PLAZA SENIOR CENTER", 
            "HOURS_OPEN": null, 
            "STATE": "NY", 
            "HOURS_CLOSE": null
        }
    }, 
    {
        "attributes": {
            "CITY": "BROOKLYN", 
            "ADDRESS": "475 53RD STREET", 
            "SHELTER_NAME": "UNITED SENIOR CITIZENS CENTER", 
            "HOURS_OPEN": null, 
            "STATE": "NY", 
            "HOURS_CLOSE": null
        }
    }, 
    {
        "attributes": {
            "CITY": "BROOKLYN", 
            "ADDRESS": "430 DUMONT AVENUE", 
            "SHELTER_NAME": "VAN DYKE SENIOR CENTER", 
            "HOURS_OPEN": null, 
            "STATE": "NY", 
            "HOURS_CLOSE": null
        }
    }, 
    {
        "attributes": {
            "CITY": "BROOKLYN", 
            "ADDRESS": "47 VANDALIA AVENUE", 
            "SHELTER_NAME": "VANDALIA SENIOR CENTER", 
            "HOURS_OPEN": null, 
            "STATE": "NY", 
            "HOURS_CLOSE": null
        }
    }, 
    {
        "attributes": {
            "CITY": "BROOKLYN", 
            "ADDRESS": "550 GREENE AVENUE", 
            "SHELTER_NAME": "WAYSIDE TOMPKINS PARK SENIOR CENTER", 
            "HOURS_OPEN": null, 
            "STATE": "NY", 
            "HOURS_CLOSE": null
        }
    }, 
    {
        "attributes": {
            "CITY": "BROOKLYN", 
            "ADDRESS": "125 HEYWARD STREET", 
            "SHELTER_NAME": "WILLIAMSBURG-SATMAR SENIOR CENTER", 
            "HOURS_OPEN": null, 
            "STATE": "NY", 
            "HOURS_CLOSE": null
        }
    }, 
    {
        "attributes": {
            "CITY": "BROOKLYN", 
            "ADDRESS": "105 NORTH PORTLAND AVENUE", 
            "SHELTER_NAME": "WILLOUGHBY SENIOR CENTER", 
            "HOURS_OPEN": null, 
            "STATE": "NY", 
            "HOURS_CLOSE": null
        }
    }, 
    {
        "attributes": {
            "CITY": "BROOKLYN", 
            "ADDRESS": "280 WYCKOFF STREET", 
            "SHELTER_NAME": "WYCKOFF GARDENS SENIOR CENTER", 
            "HOURS_OPEN": null, 
            "STATE": "NY", 
            "HOURS_CLOSE": null
        }
    }, 
    {
        "attributes": {
            "CITY": "BROOKLYN", 
            "ADDRESS": "1694 OCEAN AVENUE", 
            "SHELTER_NAME": "YOUNG ISRAEL OF MIDWOOD SENIOR CENTER", 
            "HOURS_OPEN": null, 
            "STATE": "NY", 
            "HOURS_CLOSE": null
        }
    }, 
    {
        "attributes": {
            "CITY": "MANHATTAN", 
            "ADDRESS": "108 WEST 146TH STREET", 
            "SHELTER_NAME": "A PHILIP RANDOLPH SENIOR CENTER", 
            "HOURS_OPEN": null, 
            "STATE": "NY", 
            "HOURS_CLOSE": null
        }
    }, 
    {
        "attributes": {
            "CITY": "MANHATTAN", 
            "ADDRESS": "50 W 131ST ST", 
            "SHELTER_NAME": "ABYSSINIAN TOWERS SENIOR CENTER", 
            "HOURS_OPEN": null, 
            "STATE": "NY", 
            "HOURS_CLOSE": null
        }
    }, 
    {
        "attributes": {
            "CITY": "MANHATTAN", 
            "ADDRESS": "4111 BROADWAY", 
            "SHELTER_NAME": "ARC FT WASHINGTON SENIOR CENTER", 
            "HOURS_OPEN": null, 
            "STATE": "NY", 
            "HOURS_CLOSE": null
        }
    }, 
    {
        "attributes": {
            "CITY": "MANHATTAN", 
            "ADDRESS": "221 WEST 107TH STREET", 
            "SHELTER_NAME": "ASSOC OF BLACK SOCIAL WORKERS SR CENTER", 
            "HOURS_OPEN": null, 
            "STATE": "NY", 
            "HOURS_CLOSE": null
        }
    }, 
    {
        "attributes": {
            "CITY": "MANHATTAN", 
            "ADDRESS": "30 DELANCEY STREET", 
            "SHELTER_NAME": "BRC SENIOR NUTRITION PROGRAM", 
            "HOURS_OPEN": null, 
            "STATE": "NY", 
            "HOURS_CLOSE": null
        }
    }, 
    {
        "attributes": {
            "CITY": "MANHATTAN", 
            "ADDRESS": "10 LENOX AVENUE", 
            "SHELTER_NAME": "CANAAN SENIOR SERVICE CENTER", 
            "HOURS_OPEN": null, 
            "STATE": "NY", 
            "HOURS_CLOSE": null
        }
    }, 
    {
        "attributes": {
            "CITY": "MANHATTAN", 
            "ADDRESS": "351 EAST 74TH STREET", 
            "SHELTER_NAME": "CARTER BURDEN LUNCHEON CLUB", 
            "HOURS_OPEN": null, 
            "STATE": "NY", 
            "HOURS_CLOSE": null
        }
    }, 
    {
        "attributes": {
            "CITY": "MANHATTAN", 
            "ADDRESS": "55 EAST 102ND STREET", 
            "SHELTER_NAME": "CARVER SENIOR CENTER", 
            "HOURS_OPEN": null, 
            "STATE": "NY", 
            "HOURS_CLOSE": null
        }
    }, 
    {
        "attributes": {
            "CITY": "MANHATTAN", 
            "ADDRESS": "20 WASHINGTON SQUARE NORTH", 
            "SHELTER_NAME": "CENTER ON THE SQUARE SENIOR CENTER", 
            "HOURS_OPEN": null, 
            "STATE": "NY", 
            "HOURS_CLOSE": null
        }
    }, 
    {
        "attributes": {
            "CITY": "MANHATTAN", 
            "ADDRESS": "120 WEST 140TH STREET", 
            "SHELTER_NAME": "CENTRAL HARLEM SENIOR CENTER", 
            "HOURS_OPEN": null, 
            "STATE": "NY", 
            "HOURS_CLOSE": null
        }
    }, 
    {
        "attributes": {
            "CITY": "MANHATTAN", 
            "ADDRESS": "100 GOLD STREET", 
            "SHELTER_NAME": "CITY HALL SENIOR CENTER", 
            "HOURS_OPEN": null, 
            "STATE": "NY", 
            "HOURS_CLOSE": null
        }
    }, 
    {
        "attributes": {
            "CITY": "MANHATTAN", 
            "ADDRESS": "252 W 116TH ST", 
            "SHELTER_NAME": "COMMUNITY KITCHEN OF WEST HARLEM SC", 
            "HOURS_OPEN": null, 
            "STATE": "NY", 
            "HOURS_CLOSE": null
        }
    }, 
    {
        "attributes": {
            "CITY": "MANHATTAN", 
            "ADDRESS": "307 EAST 116TH STREET", 
            "SHELTER_NAME": "CORSI HOUSE SENIOR CENTER", 
            "HOURS_OPEN": null, 
            "STATE": "NY", 
            "HOURS_CLOSE": null
        }
    }, 
    {
        "attributes": {
            "CITY": "MANHATTAN", 
            "ADDRESS": "2005 AMSTERDAM AVENUE", 
            "SHELTER_NAME": "COTHOA LUNCHEON CLUB SENIOR CENTER", 
            "HOURS_OPEN": null, 
            "STATE": "NY", 
            "HOURS_CLOSE": null
        }
    }, 
    {
        "attributes": {
            "CITY": "MANHATTAN", 
            "ADDRESS": "168 GRAND STREET", 
            "SHELTER_NAME": "CPC PROJECT OPEN DOOR", 
            "HOURS_OPEN": null, 
            "STATE": "NY", 
            "HOURS_CLOSE": null
        }
    }, 
    {
        "attributes": {
            "CITY": "MANHATTAN", 
            "ADDRESS": "3754 10TH AVENUE", 
            "SHELTER_NAME": "DYCKMAN SENIOR CENTER", 
            "HOURS_OPEN": null, 
            "STATE": "NY", 
            "HOURS_CLOSE": null
        }
    }, 
    {
        "attributes": {
            "CITY": "MANHATTAN", 
            "ADDRESS": "150 EAST 121ST STREET", 
            "SHELTER_NAME": "E. HARLEM CNCL NUTRITION PROGRAM", 
            "HOURS_OPEN": null, 
            "STATE": "NY", 
            "HOURS_CLOSE": null
        }
    }, 
    {
        "attributes": {
            "CITY": "MANHATTAN", 
            "ADDRESS": "197 EAST BROADWAY", 
            "SHELTER_NAME": "EDUCATIONAL ALLIANCE/ Whittaker Center", 
            "HOURS_OPEN": null, 
            "STATE": "NY", 
            "HOURS_CLOSE": null
        }
    }, 
    {
        "attributes": {
            "CITY": "MANHATTAN", 
            "ADDRESS": "239 WEST 49TH STREET", 
            "SHELTER_NAME": "ENCORE LUNCHEON CLUB", 
            "HOURS_OPEN": null, 
            "STATE": "NY", 
            "HOURS_CLOSE": null
        }
    }, 
    {
        "attributes": {
            "CITY": "MANHATTAN", 
            "ADDRESS": "2029 SECOND AVENUE", 
            "SHELTER_NAME": "GAYLORD WHITE SENIOR CENTER", 
            "HOURS_OPEN": null, 
            "STATE": "NY", 
            "HOURS_CLOSE": null
        }
    }, 
    {
        "attributes": {
            "CITY": "MANHATTAN", 
            "ADDRESS": "593 COLUMBUS AVENUE", 
            "SHELTER_NAME": "GODDARD-RIVERSIDE SENIOR CENTER", 
            "HOURS_OPEN": null, 
            "STATE": "NY", 
            "HOURS_CLOSE": null
        }
    }, 
    {
        "attributes": {
            "CITY": "MANHATTAN", 
            "ADDRESS": "334 MADISON STREET", 
            "SHELTER_NAME": "GOOD COMPANIONS NUTRITION", 
            "HOURS_OPEN": null, 
            "STATE": "NY", 
            "HOURS_CLOSE": null
        }
    }, 
    {
        "attributes": {
            "CITY": "MANHATTAN", 
            "ADDRESS": "80 PITT STREET", 
            "SHELTER_NAME": "GRAND COALITION OF SENIORS SENIOR CENTER", 
            "HOURS_OPEN": null, 
            "STATE": "NY", 
            "HOURS_CLOSE": null
        }
    }, 
    {
        "attributes": {
            "CITY": "MANHATTAN", 
            "ADDRESS": "420 WEST 145TH STREET", 
            "SHELTER_NAME": "HAMILTON GRANGE SENIOR CENTER", 
            "HOURS_OPEN": null, 
            "STATE": "NY", 
            "HOURS_CLOSE": null
        }
    }, 
    {
        "attributes": {
            "CITY": "MANHATTAN", 
            "ADDRESS": "119 9TH AVENUE", 
            "SHELTER_NAME": "HUDSON GUILD SENIOR SERVICES", 
            "HOURS_OPEN": null, 
            "STATE": "NY", 
            "HOURS_CLOSE": null
        }
    }, 
    {
        "attributes": {
            "CITY": "MANHATTAN", 
            "ADDRESS": "310 GREENWICH STREET", 
            "SHELTER_NAME": "INDEPENDENCE PLAZA", 
            "HOURS_OPEN": null, 
            "STATE": "NY", 
            "HOURS_CLOSE": null
        }
    }, 
    {
        "attributes": {
            "CITY": "MANHATTAN", 
            "ADDRESS": "1301 AMSTERDAM AVENUE", 
            "SHELTER_NAME": "JACKIE ROBINSON SR CTR AT GRANT HOUSES", 
            "HOURS_OPEN": null, 
            "STATE": "NY", 
            "HOURS_CLOSE": null
        }
    }, 
    {
        "attributes": {
            "CITY": "MANHATTAN", 
            "ADDRESS": "120 WEST 76TH STREET", 
            "SHELTER_NAME": "JASA CLUB 76", 
            "HOURS_OPEN": null, 
            "STATE": "NY", 
            "HOURS_CLOSE": null
        }
    }, 
    {
        "attributes": {
            "CITY": "MANHATTAN", 
            "ADDRESS": "2205 FIRST AVENUE", 
            "SHELTER_NAME": "JEFFERSON HOUSES SENIOR CENTER", 
            "HOURS_OPEN": null, 
            "STATE": "NY", 
            "HOURS_CLOSE": null
        }
    }, 
    {
        "attributes": {
            "CITY": "MANHATTAN", 
            "ADDRESS": "103 EAST 7TH STREET", 
            "SHELTER_NAME": "JOHN PAUL II FRIENDSHIP CENTER", 
            "HOURS_OPEN": null, 
            "STATE": "NY", 
            "HOURS_CLOSE": null
        }
    }, 
    {
        "attributes": {
            "CITY": "MANHATTAN", 
            "ADDRESS": "27 BARROW STREET", 
            "SHELTER_NAME": "JUDITH WHITE SENIOR CENTER", 
            "HOURS_OPEN": null, 
            "STATE": "NY", 
            "HOURS_CLOSE": null
        }
    }, 
    {
        "attributes": {
            "CITY": "MANHATTAN", 
            "ADDRESS": "34 WEST 134TH STREET", 
            "SHELTER_NAME": "KENNEDY SENIOR CENTER", 
            "HOURS_OPEN": null, 
            "STATE": "NY", 
            "HOURS_CLOSE": null
        }
    }, 
    {
        "attributes": {
            "CITY": "MANHATTAN", 
            "ADDRESS": "280 CHERRY STREET", 
            "SHELTER_NAME": "LA GUARDIA SENIOR CENTER", 
            "HOURS_OPEN": null, 
            "STATE": "NY", 
            "HOURS_CLOSE": null
        }
    }, 
    {
        "attributes": {
            "CITY": "MANHATTAN", 
            "ADDRESS": "343 EAST 70TH STREET", 
            "SHELTER_NAME": "LENOX HILL INNOVATIVE SENIOR CENTER", 
            "HOURS_OPEN": null, 
            "STATE": "NY", 
            "HOURS_CLOSE": null
        }
    }, 
    {
        "attributes": {
            "CITY": "MANHATTAN", 
            "ADDRESS": "619 LEXINGTON AVENUE", 
            "SHELTER_NAME": "LENOX HILL SENIOR CENTER II ST. PETER'S", 
            "HOURS_OPEN": null, 
            "STATE": "NY", 
            "HOURS_CLOSE": null
        }
    }, 
    {
        "attributes": {
            "CITY": "MANHATTAN", 
            "ADDRESS": "312 EAST 109TH STREET", 
            "SHELTER_NAME": "LEONARD COVELLO SENIOR CENTER", 
            "HOURS_OPEN": null, 
            "STATE": "NY", 
            "HOURS_CLOSE": null
        }
    }, 
    {
        "attributes": {
            "CITY": "MANHATTAN", 
            "ADDRESS": "1970 AMSTERDAM AVENUE", 
            "SHELTER_NAME": "M MCLEOD BETHUNE SENIOR CENTER", 
            "HOURS_OPEN": null, 
            "STATE": "NY", 
            "HOURS_CLOSE": null
        }
    }, 
    {
        "attributes": {
            "CITY": "MANHATTAN", 
            "ADDRESS": "3333 BROADWAY", 
            "SHELTER_NAME": "MANHATTANVILLE-RIVERSIDE SENIOR CENTER", 
            "HOURS_OPEN": null, 
            "STATE": "NY", 
            "HOURS_CLOSE": null
        }
    }, 
    {
        "attributes": {
            "CITY": "MANHATTAN", 
            "ADDRESS": "90 BENNETT AVENUE", 
            "SHELTER_NAME": "MORIAH OLDER ADULT LUNCHEON CLUB", 
            "HOURS_OPEN": null, 
            "STATE": "NY", 
            "HOURS_CLOSE": null
        }
    }, 
    {
        "attributes": {
            "CITY": "MANHATTAN", 
            "ADDRESS": "180 MOTT STREET", 
            "SHELTER_NAME": "MOTT STREET SENIOR CENTER", 
            "HOURS_OPEN": null, 
            "STATE": "NY", 
            "HOURS_CLOSE": null
        }
    }, 
    {
        "attributes": {
            "CITY": "MANHATTAN", 
            "ADDRESS": "70 MULBERRY STREET", 
            "SHELTER_NAME": "NY CHINATOWN SENIOR CENTER", 
            "HOURS_OPEN": null, 
            "STATE": "NY", 
            "HOURS_CLOSE": null
        }
    }, 
    {
        "attributes": {
            "CITY": "MANHATTAN", 
            "ADDRESS": "25 CARMINE STREET", 
            "SHELTER_NAME": "OUR LADY OF POMPEII SENIOR CENTER", 
            "HOURS_OPEN": null, 
            "STATE": "NY", 
            "HOURS_CLOSE": null
        }
    }, 
    {
        "attributes": {
            "CITY": "MANHATTAN", 
            "ADDRESS": "530 WEST 55TH STREET", 
            "SHELTER_NAME": "PROJECT FIND CLINTON SENIOR CENTER", 
            "HOURS_OPEN": null, 
            "STATE": "NY", 
            "HOURS_CLOSE": null
        }
    }, 
    {
        "attributes": {
            "CITY": "MANHATTAN", 
            "ADDRESS": "551 NINTH AVENUE", 
            "SHELTER_NAME": "PROJECT FIND COFFEEHOUSE SENIOR CENTER", 
            "HOURS_OPEN": null, 
            "STATE": "NY", 
            "HOURS_CLOSE": null
        }
    }, 
    {
        "attributes": {
            "CITY": "MANHATTAN", 
            "ADDRESS": "141 WEST 73RD STREET", 
            "SHELTER_NAME": "PROJECT FIND HAMILTON HOUSE", 
            "HOURS_OPEN": null, 
            "STATE": "NY", 
            "HOURS_CLOSE": null
        }
    }, 
    {
        "attributes": {
            "CITY": "MANHATTAN", 
            "ADDRESS": "127 WEST 43RD STREET", 
            "SHELTER_NAME": "PROJECT FIND WOODSTOCK SENIOR CENTER", 
            "HOURS_OPEN": null, 
            "STATE": "NY", 
            "HOURS_CLOSE": null
        }
    }, 
    {
        "attributes": {
            "CITY": "MANHATTAN", 
            "ADDRESS": "84 VERMILYEA AVE", 
            "SHELTER_NAME": "RAIN INWOOD SENIOR CENTER", 
            "HOURS_OPEN": null, 
            "STATE": "NY", 
            "HOURS_CLOSE": null
        }
    }, 
    {
        "attributes": {
            "CITY": "MANHATTAN", 
            "ADDRESS": "99 FORT WASHINGTON AVENUE", 
            "SHELTER_NAME": "RIVERSTONE SENIOR LIFE SERVICES SR CTR", 
            "HOURS_OPEN": null, 
            "STATE": "NY", 
            "HOURS_CLOSE": null
        }
    }, 
    {
        "attributes": {
            "CITY": "MANHATTAN", 
            "ADDRESS": "546 MAIN STREET", 
            "SHELTER_NAME": "ROOSEVELT ISLAND SENIOR CENTER", 
            "HOURS_OPEN": null, 
            "STATE": "NY", 
            "HOURS_CLOSE": null
        }
    }, 
    {
        "attributes": {
            "CITY": "MANHATTAN", 
            "ADDRESS": "305 SEVENTH AVENUE", 
            "SHELTER_NAME": "SAGE INNOVATIVE SENIOR CENTER", 
            "HOURS_OPEN": null, 
            "STATE": "NY", 
            "HOURS_CLOSE": null
        }
    }, 
    {
        "attributes": {
            "CITY": "MANHATTAN", 
            "ADDRESS": "331 EAST 12TH STREET", 
            "SHELTER_NAME": "SIROVICH SENIOR CENTER", 
            "HOURS_OPEN": null, 
            "STATE": "NY", 
            "HOURS_CLOSE": null
        }
    }, 
    {
        "attributes": {
            "CITY": "MANHATTAN", 
            "ADDRESS": "415 EAST 93RD STREET", 
            "SHELTER_NAME": "STANLEY ISAACS SENIOR CENTER", 
            "HOURS_OPEN": null, 
            "STATE": "NY", 
            "HOURS_CLOSE": null
        }
    }, 
    {
        "attributes": {
            "CITY": "MANHATTAN", 
            "ADDRESS": "245 EAST 17TH STREET (temporary)", 
            "SHELTER_NAME": "STEIN SENIOR CENTER", 
            "HOURS_OPEN": null, 
            "STATE": "NY", 
            "HOURS_CLOSE": null
        }
    }, 
    {
        "attributes": {
            "CITY": "MANHATTAN", 
            "ADDRESS": "2322 THIRD AVENUE", 
            "SHELTER_NAME": "UBA BEATRICE LEWIS SENIOR CENTER", 
            "HOURS_OPEN": null, 
            "STATE": "NY", 
            "HOURS_CLOSE": null
        }
    }, 
    {
        "attributes": {
            "CITY": "MANHATTAN", 
            "ADDRESS": "15 BIALYSTOKER PLACE", 
            "SHELTER_NAME": "UJC ADULT LUNCHEON CLUB", 
            "HOURS_OPEN": null, 
            "STATE": "NY", 
            "HOURS_CLOSE": null
        }
    }, 
    {
        "attributes": {
            "CITY": "MANHATTAN", 
            "ADDRESS": "189 ALLEN STREET", 
            "SHELTER_NAME": "UNIVERSITY SETTLEMENT NUTRITION", 
            "HOURS_OPEN": null, 
            "STATE": "NY", 
            "HOURS_CLOSE": null
        }
    }, 
    {
        "attributes": {
            "CITY": "MANHATTAN", 
            "ADDRESS": "135 WEST 23RD STREET", 
            "SHELTER_NAME": "VISIONS INNOVATIVE SENIOR CENTER", 
            "HOURS_OPEN": null, 
            "STATE": "NY", 
            "HOURS_CLOSE": null
        }
    }, 
    {
        "attributes": {
            "CITY": "MANHATTAN", 
            "ADDRESS": "650 WEST 187TH STREET", 
            "SHELTER_NAME": "WASH HGTS COMMUNITY SVC SENIOR CENTER", 
            "HOURS_OPEN": null, 
            "STATE": "NY", 
            "HOURS_CLOSE": null
        }
    }, 
    {
        "attributes": {
            "CITY": "MANHATTAN", 
            "ADDRESS": "250 W 65TH ST", 
            "SHELTER_NAME": "WEST 65TH STREET SENIOR CENTER", 
            "HOURS_OPEN": null, 
            "STATE": "NY", 
            "HOURS_CLOSE": null
        }
    }, 
    {
        "attributes": {
            "CITY": "MANHATTAN", 
            "ADDRESS": "135 WEST 106TH STREET", 
            "SHELTER_NAME": "WEST SIDE FEDERATION SENIOR CENTER", 
            "HOURS_OPEN": null, 
            "STATE": "NY", 
            "HOURS_CLOSE": null
        }
    }, 
    {
        "attributes": {
            "CITY": "MANHATTAN", 
            "ADDRESS": "54 NAGLE AVENUE", 
            "SHELTER_NAME": "YM YWHA INNOVATIVE SENIOR CENTER", 
            "HOURS_OPEN": null, 
            "STATE": "NY", 
            "HOURS_CLOSE": null
        }
    }, 
    {
        "attributes": {
            "CITY": "QUEENS", 
            "ADDRESS": "166-01 LINDEN BOULEVARD", 
            "SHELTER_NAME": "ALLEN COMMUNITY SENIOR CITIZENS CENTER", 
            "HOURS_OPEN": null, 
            "STATE": "NY", 
            "HOURS_CLOSE": null
        }
    }, 
    {
        "attributes": {
            "CITY": "QUEENS", 
            "ADDRESS": "220-01 LINDEN BOULVARD", 
            "SHELTER_NAME": "ALPHA PHI ALPHA SENIOR CENTER", 
            "HOURS_OPEN": null, 
            "STATE": "NY", 
            "HOURS_CLOSE": null
        }
    }, 
    {
        "attributes": {
            "CITY": "QUEENS", 
            "ADDRESS": "143-22 109TH AVENUE", 
            "SHELTER_NAME": "BROOKS SENIOR CENTER", 
            "HOURS_OPEN": null, 
            "STATE": "NY", 
            "HOURS_CLOSE": null
        }
    }, 
    {
        "attributes": {
            "CITY": "QUEENS", 
            "ADDRESS": "221-15 HORACE HARDING EXPWY", 
            "SHELTER_NAME": "CCNS BAYSIDE SENIOR CENTER", 
            "HOURS_OPEN": null, 
            "STATE": "NY", 
            "HOURS_CLOSE": null
        }
    }, 
    {
        "attributes": {
            "CITY": "QUEENS", 
            "ADDRESS": "35-24 83RD STREET", 
            "SHELTER_NAME": "CCNS CATHERINE SHERIDAN SENIOR CENTER", 
            "HOURS_OPEN": null, 
            "STATE": "NY", 
            "HOURS_CLOSE": null
        }
    }, 
    {
        "attributes": {
            "CITY": "QUEENS", 
            "ADDRESS": "23-56 BROADWAY", 
            "SHELTER_NAME": "CCNS DELLAMONICA SENIOR CENTER", 
            "HOURS_OPEN": null, 
            "STATE": "NY", 
            "HOURS_CLOSE": null
        }
    }, 
    {
        "attributes": {
            "CITY": "QUEENS", 
            "ADDRESS": "168-01B HILLSIDE AVENUE", 
            "SHELTER_NAME": "CCNS HILLCREST SENIOR CENTER", 
            "HOURS_OPEN": null, 
            "STATE": "NY", 
            "HOURS_CLOSE": null
        }
    }, 
    {
        "attributes": {
            "CITY": "QUEENS", 
            "ADDRESS": "103-02 101ST AVENUE", 
            "SHELTER_NAME": "CCNS OZONE PARK SENIOR CENTER", 
            "HOURS_OPEN": null, 
            "STATE": "NY", 
            "HOURS_CLOSE": null
        }
    }, 
    {
        "attributes": {
            "CITY": "QUEENS", 
            "ADDRESS": "78-15 JAMAICA AVENUE", 
            "SHELTER_NAME": "CCNS WOODHAVEN RICHMOND HILL SR. CTR.", 
            "HOURS_OPEN": null, 
            "STATE": "NY", 
            "HOURS_CLOSE": null
        }
    }, 
    {
        "attributes": {
            "CITY": "QUEENS", 
            "ADDRESS": "136-18 39TH AVENUE", 
            "SHELTER_NAME": "CPC QUEENS NAN SHAN SENIOR CITIZEN CTR", 
            "HOURS_OPEN": null, 
            "STATE": "NY", 
            "HOURS_CLOSE": null
        }
    }, 
    {
        "attributes": {
            "CITY": "QUEENS", 
            "ADDRESS": "98-19 ASTORIA BOULVARD", 
            "SHELTER_NAME": "ELMCOR SENIOR CENTER", 
            "HOURS_OPEN": null, 
            "STATE": "NY", 
            "HOURS_CLOSE": null
        }
    }, 
    {
        "attributes": {
            "CITY": "QUEENS", 
            "ADDRESS": "75-01 BROADWAY", 
            "SHELTER_NAME": "ELMHURST JACKSON HEIGHTS SENIOR CENTER", 
            "HOURS_OPEN": null, 
            "STATE": "NY", 
            "HOURS_CLOSE": null
        }
    }, 
    {
        "attributes": {
            "CITY": "QUEENS", 
            "ADDRESS": "102-19 34TH AVENUE", 
            "SHELTER_NAME": "FLORENCE SMITH SENIOR SERVICE", 
            "HOURS_OPEN": null, 
            "STATE": "NY", 
            "HOURS_CLOSE": null
        }
    }, 
    {
        "attributes": {
            "CITY": "QUEENS", 
            "ADDRESS": "108-25 62ND DRIVE", 
            "SHELTER_NAME": "FOREST HILLS COMMUNITY HOUSE SENIOR CTR", 
            "HOURS_OPEN": null, 
            "STATE": "NY", 
            "HOURS_CLOSE": null
        }
    }, 
    {
        "attributes": {
            "CITY": "QUEENS", 
            "ADDRESS": "13-28 123RD STREET", 
            "SHELTER_NAME": "HANAC ANGELO PETROMELIS SENIOR CENTER", 
            "HOURS_OPEN": null, 
            "STATE": "NY", 
            "HOURS_CLOSE": null
        }
    }, 
    {
        "attributes": {
            "CITY": "QUEENS", 
            "ADDRESS": "27-40 HOYT AVENUE SOUTH", 
            "SHELTER_NAME": "HANAC LINDSAY SENIOR CENTER", 
            "HOURS_OPEN": null, 
            "STATE": "NY", 
            "HOURS_CLOSE": null
        }
    }, 
    {
        "attributes": {
            "CITY": "QUEENS", 
            "ADDRESS": "157-10 83RD STREET (temporary)", 
            "SHELTER_NAME": "CCNS HOWARD BEACH SENIOR CENTER", 
            "HOURS_OPEN": null, 
            "STATE": "NY", 
            "HOURS_CLOSE": null
        }
    }, 
    {
        "attributes": {
            "CITY": "QUEENS", 
            "ADDRESS": "108-74 ROOSEVELT AVENUE", 
            "SHELTER_NAME": "IPR HE CORONA SENIOR CENTER", 
            "HOURS_OPEN": null, 
            "STATE": "NY", 
            "HOURS_CLOSE": null
        }
    }, 
    {
        "attributes": {
            "CITY": "QUEENS", 
            "ADDRESS": "131 BEACH 19TH STREET", 
            "SHELTER_NAME": "JASA BROOKDALE SENIOR CENTER", 
            "HOURS_OPEN": null, 
            "STATE": "NY", 
            "HOURS_CLOSE": null
        }
    }, 
    {
        "attributes": {
            "CITY": "QUEENS", 
            "ADDRESS": "86-25 FRANCIS LEWIS BLVD", 
            "SHELTER_NAME": "JASA HOLLISWOOD SENIOR CENTER", 
            "HOURS_OPEN": null, 
            "STATE": "NY", 
            "HOURS_CLOSE": null
        }
    }, 
    {
        "attributes": {
            "CITY": "QUEENS", 
            "ADDRESS": "106-20 SHORE FRONT PKWY.", 
            "SHELTER_NAME": "JASA ROCKAWAY PARK SENIOR CENTER", 
            "HOURS_OPEN": null, 
            "STATE": "NY", 
            "HOURS_CLOSE": null
        }
    }, 
    {
        "attributes": {
            "CITY": "QUEENS", 
            "ADDRESS": "7-11C SEAGIRT AVENUE", 
            "SHELTER_NAME": "JASA ROY REUTHER SENIOR CENTER", 
            "HOURS_OPEN": null, 
            "STATE": "NY", 
            "HOURS_CLOSE": null
        }
    }, 
    {
        "attributes": {
            "CITY": "QUEENS", 
            "ADDRESS": "92-33 170TH STREET", 
            "SHELTER_NAME": "JSPOA FRIENDSHIP NUTRITION CENTER", 
            "HOURS_OPEN": null, 
            "STATE": "NY", 
            "HOURS_CLOSE": null
        }
    }, 
    {
        "attributes": {
            "CITY": "QUEENS", 
            "ADDRESS": "123-10 143RD STREET", 
            "SHELTER_NAME": "JSPOA ROCKAWAY BLVD SENIOR CENTER", 
            "HOURS_OPEN": null, 
            "STATE": "NY", 
            "HOURS_CLOSE": null
        }
    }, 
    {
        "attributes": {
            "CITY": "QUEENS", 
            "ADDRESS": "92-47 165TH STREET", 
            "SHELTER_NAME": "JSPOA THEODORA JACKSON SENIOR CENTER", 
            "HOURS_OPEN": null, 
            "STATE": "NY", 
            "HOURS_CLOSE": null
        }
    }, 
    {
        "attributes": {
            "CITY": "QUEENS", 
            "ADDRESS": "37-06 111TH STREET", 
            "SHELTER_NAME": "KOREAN AMERICAN SENIOR CENTER", 
            "HOURS_OPEN": null, 
            "STATE": "NY", 
            "HOURS_CLOSE": null
        }
    }, 
    {
        "attributes": {
            "CITY": "QUEENS", 
            "ADDRESS": "42-15 166TH STREET", 
            "SHELTER_NAME": "KOREAN AMERICAN SENIOR CENTER - FLUSHING", 
            "HOURS_OPEN": null, 
            "STATE": "NY", 
            "HOURS_CLOSE": null
        }
    }, 
    {
        "attributes": {
            "CITY": "QUEENS", 
            "ADDRESS": "98-16 55TH AVENUE", 
            "SHELTER_NAME": "LEFRAK SENIOR CITIZENS CENTER", 
            "HOURS_OPEN": null, 
            "STATE": "NY", 
            "HOURS_CLOSE": null
        }
    }, 
    {
        "attributes": {
            "CITY": "QUEENS", 
            "ADDRESS": "69-10 75TH STREET", 
            "SHELTER_NAME": "MIDDLE VILLAGE OLDER ADULT CENTER", 
            "HOURS_OPEN": null, 
            "STATE": "NY", 
            "HOURS_CLOSE": null
        }
    }, 
    {
        "attributes": {
            "CITY": "QUEENS", 
            "ADDRESS": "83-20 QUEENS BOULEVARD", 
            "SHELTER_NAME": "NEWTOWN ITALIAN SENIOR CENTER", 
            "HOURS_OPEN": null, 
            "STATE": "NY", 
            "HOURS_CLOSE": null
        }
    }, 
    {
        "attributes": {
            "CITY": "QUEENS", 
            "ADDRESS": "68-52 FRESH POND ROAD", 
            "SHELTER_NAME": "PETER CARDELLA SENIOR CITIZEN CENTER", 
            "HOURS_OPEN": null, 
            "STATE": "NY", 
            "HOURS_CLOSE": null
        }
    }, 
    {
        "attributes": {
            "CITY": "QUEENS", 
            "ADDRESS": "67-09 KISSENA BOULEVARD", 
            "SHELTER_NAME": "POMONOK SENIOR CENTER", 
            "HOURS_OPEN": null, 
            "STATE": "NY", 
            "HOURS_CLOSE": null
        }
    }, 
    {
        "attributes": {
            "CITY": "QUEENS", 
            "ADDRESS": "10-25 41ST AVENUE", 
            "SHELTER_NAME": "QUEENSBRIDGE-RIIS SENIOR CENTER", 
            "HOURS_OPEN": null, 
            "STATE": "NY", 
            "HOURS_CLOSE": null
        }
    }, 
    {
        "attributes": {
            "CITY": "QUEENS", 
            "ADDRESS": "21-21 30TH DRIVE", 
            "SHELTER_NAME": "RAICES ASTORIA SENIOR CENTER", 
            "HOURS_OPEN": null, 
            "STATE": "NY", 
            "HOURS_CLOSE": null
        }
    }, 
    {
        "attributes": {
            "CITY": "QUEENS", 
            "ADDRESS": "107-24 CORONA AVENUE", 
            "SHELTER_NAME": "RAICES CORONA SENIOR CENTER", 
            "HOURS_OPEN": null, 
            "STATE": "NY", 
            "HOURS_CLOSE": null
        }
    }, 
    {
        "attributes": {
            "CITY": "QUEENS", 
            "ADDRESS": "34-35A 12TH STREET", 
            "SHELTER_NAME": "RAVENSWOOD SENIOR CENTER", 
            "HOURS_OPEN": null, 
            "STATE": "NY", 
            "HOURS_CLOSE": null
        }
    }, 
    {
        "attributes": {
            "CITY": "QUEENS", 
            "ADDRESS": "93-29 QUEENS BOULEVARD", 
            "SHELTER_NAME": "REGO PARK SENIOR CENTER", 
            "HOURS_OPEN": null, 
            "STATE": "NY", 
            "HOURS_CLOSE": null
        }
    }, 
    {
        "attributes": {
            "CITY": "QUEENS", 
            "ADDRESS": "59-14 70TH AVENUE", 
            "SHELTER_NAME": "RIDGEWOOD OLDER ADULT CENTER", 
            "HOURS_OPEN": null, 
            "STATE": "NY", 
            "HOURS_CLOSE": null
        }
    }, 
    {
        "attributes": {
            "CITY": "QUEENS", 
            "ADDRESS": "137-57 FARMERS BOULEVARD", 
            "SHELTER_NAME": "ROBERT COUCHE SENIOR CITIZEN CENTER", 
            "HOURS_OPEN": null, 
            "STATE": "NY", 
            "HOURS_CLOSE": null
        }
    }, 
    {
        "attributes": {
            "CITY": "QUEENS", 
            "ADDRESS": "169-65 137TH AVENUE", 
            "SHELTER_NAME": "ROCHDALE SENIOR CENTER", 
            "HOURS_OPEN": null, 
            "STATE": "NY", 
            "HOURS_CLOSE": null
        }
    }, 
    {
        "attributes": {
            "CITY": "QUEENS", 
            "ADDRESS": "58-20 LITTLE NECK PARKWAY", 
            "SHELTER_NAME": "SAMUEL FIELD NEIGHBORHOOD SENIOR CENTER", 
            "HOURS_OPEN": null, 
            "STATE": "NY", 
            "HOURS_CLOSE": null
        }
    }, 
    {
        "attributes": {
            "CITY": "QUEENS", 
            "ADDRESS": "106-06 QUEENS BOULEVARD", 
            "SHELTER_NAME": "SELFHELP AUSTIN ST SENIOR CENTER", 
            "HOURS_OPEN": null, 
            "STATE": "NY", 
            "HOURS_CLOSE": null
        }
    }, 
    {
        "attributes": {
            "CITY": "QUEENS", 
            "ADDRESS": "208-11 26TH AVENUE", 
            "SHELTER_NAME": "SELFHELP CLEARVIEW SENIOR CENTER", 
            "HOURS_OPEN": null, 
            "STATE": "NY", 
            "HOURS_CLOSE": null
        }
    }, 
    {
        "attributes": {
            "CITY": "QUEENS", 
            "ADDRESS": "45-25 KISSENA BOULEVARD", 
            "SHELTER_NAME": "SELFHELP INNOVATIVE SENIOR CENTER", 
            "HOURS_OPEN": null, 
            "STATE": "NY", 
            "HOURS_CLOSE": null
        }
    }, 
    {
        "attributes": {
            "CITY": "QUEENS", 
            "ADDRESS": "34-30 137 STREET", 
            "SHELTER_NAME": "SELFHELP LATIMER GARDENS SENIOR CENTER", 
            "HOURS_OPEN": null, 
            "STATE": "NY", 
            "HOURS_CLOSE": null
        }
    }, 
    {
        "attributes": {
            "CITY": "QUEENS", 
            "ADDRESS": "69-61 GRAND AVENUE", 
            "SHELTER_NAME": "SELFHELP MASPETH SENIOR CENTER", 
            "HOURS_OPEN": null, 
            "STATE": "NY", 
            "HOURS_CLOSE": null
        }
    }, 
    {
        "attributes": {
            "CITY": "QUEENS", 
            "ADDRESS": "133-33 BROOKVILLE BOULEVARD", 
            "SHELTER_NAME": "SNAP BROOKVILLE SENIOR CENTER", 
            "HOURS_OPEN": null, 
            "STATE": "NY", 
            "HOURS_CLOSE": null
        }
    }, 
    {
        "attributes": {
            "CITY": "QUEENS", 
            "ADDRESS": "80-45 WINCHESTER BOULEVARD", 
            "SHELTER_NAME": "SNAP INNOVATIVE SENIOR CENTER", 
            "HOURS_OPEN": null, 
            "STATE": "NY", 
            "HOURS_CLOSE": null
        }
    }, 
    {
        "attributes": {
            "CITY": "QUEENS", 
            "ADDRESS": "43-31 39TH STREET", 
            "SHELTER_NAME": "SUNNYSIDE COMMUNITY SENIOR CENTER", 
            "HOURS_OPEN": null, 
            "STATE": "NY", 
            "HOURS_CLOSE": null
        }
    }, 
    {
        "attributes": {
            "CITY": "QUEENS", 
            "ADDRESS": "50-37 NEWTOWN ROAD", 
            "SHELTER_NAME": "WOODSIDE SENIOR CENTER", 
            "HOURS_OPEN": null, 
            "STATE": "NY", 
            "HOURS_CLOSE": null
        }
    }, 
    {
        "attributes": {
            "CITY": "QUEENS", 
            "ADDRESS": "2716 HEALY AVENUE", 
            "SHELTER_NAME": "YNG ISRAEL WAVECREST BAYSWATER SR LEAGUE", 
            "HOURS_OPEN": null, 
            "STATE": "NY", 
            "HOURS_CLOSE": null
        }
    }, 
    {
        "attributes": {
            "CITY": "QUEENS", 
            "ADDRESS": "68-07 BURNS STREET", 
            "SHELTER_NAME": "YOUNG ISRAEL FOREST HILLS SENIOR LEAGUE", 
            "HOURS_OPEN": null, 
            "STATE": "NY", 
            "HOURS_CLOSE": null
        }
    }, 
    {
        "attributes": {
            "CITY": "QUEENS", 
            "ADDRESS": "141-55 77TH AVENUE", 
            "SHELTER_NAME": "YOUNG ISRAEL QUEENS VALLEY", 
            "HOURS_OPEN": null, 
            "STATE": "NY", 
            "HOURS_CLOSE": null
        }
    }, 
    {
        "attributes": {
            "CITY": "STATEN ISLAND", 
            "ADDRESS": "120 ANDERSON AVENUE", 
            "SHELTER_NAME": "ANDERSON NEIGHBORHOOD SENIOR CENTER", 
            "HOURS_OPEN": null, 
            "STATE": "NY", 
            "HOURS_CLOSE": null
        }
    }, 
    {
        "attributes": {
            "CITY": "STATEN ISLAND", 
            "ADDRESS": "85 JEROME AVENUE", 
            "SHELTER_NAME": "ARROCHAR FRIENDSHIP CLUB SENIOR CENTER", 
            "HOURS_OPEN": null, 
            "STATE": "NY", 
            "HOURS_CLOSE": null
        }
    }, 
    {
        "attributes": {
            "CITY": "STATEN ISLAND", 
            "ADDRESS": "125 CASSIDY PLACE", 
            "SHELTER_NAME": "CASSIDY COLES SENIOR CENTER", 
            "HOURS_OPEN": null, 
            "STATE": "NY", 
            "HOURS_CLOSE": null
        }
    }, 
    {
        "attributes": {
            "CITY": "STATEN ISLAND", 
            "ADDRESS": "1466 MANOR ROAD", 
            "SHELTER_NAME": "JCC OF STATEN ISLAND INNOVATIVE SR CTR", 
            "HOURS_OPEN": null, 
            "STATE": "NY", 
            "HOURS_CLOSE": null
        }
    }, 
    {
        "attributes": {
            "CITY": "STATEN ISLAND", 
            "ADDRESS": "1297 ARTHUR KILL ROAD", 
            "SHELTER_NAME": "JCC SOUTH SHORE SR CTR", 
            "HOURS_OPEN": null, 
            "STATE": "NY", 
            "HOURS_CLOSE": null
        }
    }, 
    {
        "attributes": {
            "CITY": "STATEN ISLAND", 
            "ADDRESS": "6581 HYLAN BOULEVARD", 
            "SHELTER_NAME": "MOUNT LORETTO FRIENDSHIP CLUB SENIOR CTR", 
            "HOURS_OPEN": null, 
            "STATE": "NY", 
            "HOURS_CLOSE": null
        }
    }, 
    {
        "attributes": {
            "CITY": "STATEN ISLAND", 
            "ADDRESS": "70 NEW LANE", 
            "SHELTER_NAME": "NEW LANE SENIOR CENTER", 
            "HOURS_OPEN": null, 
            "STATE": "NY", 
            "HOURS_CLOSE": null
        }
    }, 
    {
        "attributes": {
            "CITY": "STATEN ISLAND", 
            "ADDRESS": "189 GORDON STREET", 
            "SHELTER_NAME": "STAPLETON SENIOR CENTER", 
            "HOURS_OPEN": null, 
            "STATE": "NY", 
            "HOURS_CLOSE": null
        }
    }, 
    {
        "attributes": {
            "CITY": "STATEN ISLAND", 
            "ADDRESS": "11 SAMPSON AVENUE", 
            "SHELTER_NAME": "STATEN ISLAND FRIENDSHIP CLUB", 
            "HOURS_OPEN": null, 
            "STATE": "NY", 
            "HOURS_CLOSE": null
        }
    }, 
    {
        "attributes": {
            "CITY": "STATEN ISLAND", 
            "ADDRESS": "184 SCHMIDTS LANE", 
            "SHELTER_NAME": "TODT HILL FRIENDSHIP CLUB SENIOR CENTER", 
            "HOURS_OPEN": null, 
            "STATE": "NY", 
            "HOURS_CLOSE": null
        }
    }, 
    {
        "attributes": {
            "CITY": "STATEN ISLAND", 
            "ADDRESS": "230 BROADWAY", 
            "SHELTER_NAME": "WEST BRIGHTON SENIOR CENTER", 
            "HOURS_OPEN": null, 
            "STATE": "NY", 
            "HOURS_CLOSE": null
        }
    }
]